mllopenai/__init__.py
mllopenai/main.py
mllopenaimanager-1.1.0.dist-info/LICENCE.txt
mllopenaimanager-1.1.0.dist-info/METADATA
mllopenaimanager-1.1.0.dist-info/WHEEL
mllopenaimanager-1.1.0.dist-info/top_level.txt
mllopenaimanager-1.1.0.dist-info/RECORD
