Metadata-Version: 2.1
Name: mllopenaimanager
Version: 1.1.0
License-File: LICENCE.txt
Requires-Dist: openai >=1.12.0
Requires-Dist: tiktoken >=0.6.0
